Metadata-Version: 1.1
Name: jupyterhub-hook-filemanager
Version: 0.0.2
Summary: Content Manager FileManager for jupyterhub with hooks.
Home-page: https://github.com/globocom/jupyterhub_hook_filemanager
Author: Globo.com
Author-email: diogo.munaro@corp.globo.com
License: UNKNOWN
Keywords: Interactive,Interpreter,Shell,Web,Customization,JupyterHub
Platform: Linux
Platform: Mac OS X
Classifier: Intended Audience :: Developers
Classifier: Intended Audience :: System Administrators
Classifier: Intended Audience :: Science/Research
Classifier: Programming Language :: Python
Classifier: Programming Language :: Python :: 3
